{
  "users": [
    {
      "email": "sdasd@example.it",
      "password": "$2a$10$XEj0F0IzhMrAETKx3cFZMuPeVtWrjjw4H3rs.xlhsbE3.vrV8uiTW",
      "name": "dsdas",
      "id": 1
    },
    {
      "email": "example@example.it",
      "password": "$2a$10$y2z7uzh1vdfRRSnvVX9MUucSzWrGKh6lC2f0CVz3qBsDED449K9dO",
      "name": "dsfdsfs",
      "id": 2
    },
    {
      "email": "danydifilippo@gmail.com",
      "password": "$2a$10$X83cRV05a0Gag2umXkLpAuGVt9Rko/erCY/9ym7eUVnqObRQiR5bK",
      "name": "dsadsd",
      "id": 3
    },
    {
      "email": "Jarvis_IT_27@maildrop.cc",
      "password": "$2a$10$VSdAJrbgJdfqVlFD4i7nleYXQ5kY6Wj0ZX0n8AfcmvaiHlirJuGtq",
      "name": "sdsfdfs",
      "id": 4
    },
    {
      "email": "danielepietro@hotmail.it",
      "password": "$2a$10$.vf/bK0j1EU8ncOz8RLD7OnZDocMJFkSEMwoY2h3IiFSGwmQDgBNW",
      "name": "Daniela Di Filippo",
      "id": 5
    },
    {
      "email": "danielepietro@gmail.com",
      "password": "$2a$10$AFRP4mpOFQyLzlCKByiA4eFvHh3vSash5G6uVxOq53fKuquKdAaye",
      "name": "Pietro Daniele",
      "id": 6
    },
    {
      "email": "info@tredaniele.it",
      "password": "$2a$10$ZjbgVuWmoqkWif/CxgSYPeI9yw46PBIibBFhuU2xDnkwQbOPPJP7i",
      "name": "Gianni Daniele",
      "id": 7
    },
    {
      "email": "danydifilippo@yahoo.it",
      "password": "$2a$10$SOh/kICL9mxtTC3lncSK0uS9HjTp3WGy1TvmGB5FL/f/BadQNcjk6",
      "name": "Daniela Di Filippo",
      "id": 8
    },
    {
      "email": "nnn@nnn.it",
      "password": "$2a$10$fS.T.pkYbTFsuOZ3maQAW.UqGd8f1HQ9HkINpo0dZPDqDNFfaJ3H2",
      "name": "Mario Rossi",
      "id": 9
    },
    {
      "email": "paolo@example.it",
      "password": "$2a$10$J66.UaAKj0fAIFxJgr0cGuLEFL9GwcEfF5o1t38c6b8EP7vslZhhu",
      "name": "Paolo Rossi",
      "id": 10
    }
  ]
}
